{
  "poses": {
    "pose": [
      {
        "reachPose": {
          "targetPose": {
            "x": 0.511,
            "y": 0.352,
            "z": 0.066,
            "thetaX": 90.589,
            "thetaY": 3.413,
            "thetaZ": 129.705
          },
          "constraint": {
            "speed": {
              "translation": 0.3,
              "orientation": 0
            }
          }
        },
        "applicationData": "{\"kinova\":{\"color\":0}}",
        "handle": {
          "identifier": 10003,
          "permission": 7,
          "actionType": 6
        },
        "name": "Potentiostat Elevator 1"
      }
    ]
  }
}